genvexnabto/__init__.py
genvexnabto/const.py
genvexnabto/genvexnabto.py
genvexnabto/genvexnabto_modeladapter.py
genvexnabto/models/__init__.py
genvexnabto/models/basemodel.py
genvexnabto/models/cts400.py
genvexnabto/models/cts602.py
genvexnabto/models/cts602light.py
genvexnabto/models/optima250.py
genvexnabto/models/optima251.py
genvexnabto/models/optima260.py
genvexnabto/models/optima270.py
genvexnabto/models/optima301.py
genvexnabto/models/optima312.py
genvexnabto/models/optima314.py
genvexnabto/protocol/__init__.py
genvexnabto/protocol/cmd_datapoint_readlist.py
genvexnabto/protocol/cmd_keepalive.py
genvexnabto/protocol/cmd_ping.py
genvexnabto/protocol/cmd_setpoint_readlist.py
genvexnabto/protocol/cmd_setpoint_writelist.py
genvexnabto/protocol/discovery.py
genvexnabto/protocol/packet.py
genvexnabto/protocol/packet_keepalive.py
genvexnabto/protocol/payload.py
genvexnabto/protocol/payload_cp_id.py
genvexnabto/protocol/payload_crypt.py
genvexnabto/protocol/payload_ipx.py
genvexnabto-1.4.4.dist-info/licenses/LICENSE
genvexnabto-1.4.4.dist-info/METADATA
genvexnabto-1.4.4.dist-info/WHEEL
genvexnabto-1.4.4.dist-info/top_level.txt
genvexnabto-1.4.4.dist-info/RECORD
