Metadata-Version: 2.4
Name: genvexnabto
Version: 1.4.4
Summary: A library to interface with Genvex Connect enabled ventilation units.
Home-page: https://github.com/superrob/genvexnabto
Author: Superrob
Author-email: robin@robserob.dk
License: GPLv3
Keywords: Genvex,Genvex Connect,Nabto,Optima 270,Optima 260,Optima 251,Optima 250,library,Home Automation,Nilan,CTS 602,CTS 400
Classifier: Development Status :: 3 - Alpha
Classifier: Programming Language :: Python :: 3.9
Classifier: Intended Audience :: Developers
Classifier: Topic :: Software Development :: Libraries
Classifier: License :: OSI Approved :: GNU General Public License v3 (GPLv3)
Requires-Python: >=3.9
License-File: LICENSE
Dynamic: license-file
